inventree/__init__.py
inventree/api.py
inventree/base.py
inventree/build.py
inventree/company.py
inventree/currency.py
inventree/label.py
inventree/order.py
inventree/part.py
inventree/plugin.py
inventree/project_code.py
inventree/purchase_order.py
inventree/report.py
inventree/return_order.py
inventree/sales_order.py
inventree/stock.py
inventree/user.py
inventree-0.21.1.dist-info/licenses/LICENSE
inventree-0.21.1.dist-info/METADATA
inventree-0.21.1.dist-info/WHEEL
inventree-0.21.1.dist-info/top_level.txt
inventree-0.21.1.dist-info/RECORD
