Metadata-Version: 2.4
Name: inventree
Version: 0.21.1
Summary: Python interface for InvenTree inventory management system
Author-email: Oliver Walters <oliver.henry.walters@gmail.com>
License: MIT License
Project-URL: Homepage, https://github.com/inventree/inventree-python/
Keywords: barcode,bill,bom,inventory,management,materials,of,stock
Requires-Python: >=3.9
License-File: LICENSE
Requires-Dist: requests>=2.27.0
Requires-Dist: urllib3>=2.3.0
Provides-Extra: system-certs
Requires-Dist: pip-system-certs>=4.0; extra == "system-certs"
Dynamic: license-file
